tugboat/__init__.py
tugboat/_vendor/__init__.py
tugboat/_vendor/glob.py
tugboat/_vendor/lolcat.py
tugboat/_vendor/pygments/README.md
tugboat/_vendor/pygments/__init__.py
tugboat/_vendor/pygments/filter.py
tugboat/_vendor/pygments/filters.py
tugboat/_vendor/pygments/lexer.py
tugboat/_vendor/pygments/plugin.py
tugboat/_vendor/pygments/regexopt.py
tugboat/_vendor/pygments/token.py
tugboat/_vendor/pygments/util.py
tugboat/_vendor/termcolors.py
tugboat/analyzers/__init__.py
tugboat/analyzers/container.py
tugboat/analyzers/cron_workflow.py
tugboat/analyzers/kubernetes.py
tugboat/analyzers/metrics.py
tugboat/analyzers/step.py
tugboat/analyzers/template/__init__.py
tugboat/analyzers/template/inputs.py
tugboat/analyzers/template/outputs.py
tugboat/analyzers/workflow.py
tugboat/analyzers/workflow_template.py
tugboat/console/__init__.py
tugboat/console/anchor.py
tugboat/console/formatters/__init__.py
tugboat/console/formatters/base.py
tugboat/console/formatters/console.py
tugboat/console/formatters/github.py
tugboat/console/formatters/junit.py
tugboat/console/glob.py
tugboat/console/mcp.py
tugboat/console/utils.py
tugboat/constraints.py
tugboat/core.py
tugboat/engine/__init__.py
tugboat/engine/helpers.py
tugboat/engine/linecol.py
tugboat/engine/mainfest.py
tugboat/engine/types.py
tugboat/hookspecs/__init__.py
tugboat/hookspecs/core.py
tugboat/hookspecs/workflow.py
tugboat/parsers/__init__.py
tugboat/parsers/ast/__init__.py
tugboat/parsers/ast/argo_template.py
tugboat/parsers/ast/core.py
tugboat/parsers/lexer.py
tugboat/references/__init__.py
tugboat/references/cache.py
tugboat/references/context.py
tugboat/references/step.py
tugboat/references/template.py
tugboat/references/workflow.py
tugboat/schemas/__init__.py
tugboat/schemas/arguments/__init__.py
tugboat/schemas/arguments/artifact.py
tugboat/schemas/arguments/parameter.py
tugboat/schemas/basic.py
tugboat/schemas/cron_workflow.py
tugboat/schemas/debug.py
tugboat/schemas/manifest.py
tugboat/schemas/metrics.py
argo_tugboat-0.6.3.dist-info/METADATA
argo_tugboat-0.6.3.dist-info/WHEEL
argo_tugboat-0.6.3.dist-info/entry_points.txt
argo_tugboat-0.6.3.dist-info/RECORD
